iamzero_botocore/__init__.py
iamzero_botocore/config.py
iamzero_botocore/logging.py
iamzero_botocore/monitor.py
iamzero_botocore/session.py
iamzero_botocore-0.1.10.dist-info/WHEEL
iamzero_botocore-0.1.10.dist-info/METADATA
iamzero_botocore-0.1.10.dist-info/RECORD
