Metadata-Version: 2.1
Name: iamzero-botocore
Version: 0.1.10
Summary: iam-zero instrumentation for AWS botocore
License: Apache-2.0
Author: Chris Norman
Author-email: chris@exponentlabs.io
Requires-Python: >=3.6.2,<4.0.0
Classifier: License :: OSI Approved :: Apache Software License
Classifier: Programming Language :: Python :: 3
Classifier: Programming Language :: Python :: 3.7
Classifier: Programming Language :: Python :: 3.8
Classifier: Programming Language :: Python :: 3.9
Requires-Dist: botocore (>=1.20.54,<2.0.0)
Requires-Dist: requests (>=2.25.1,<3.0.0)
